{"body":"# OpenLinkedIn\r\n\r\nThis app handles LinkedIn's proprietary `linkedin://#profile` URL and opens the default web browser to show that person's LinkedIn profile. You get these proprietary URLs as your contacts' home page when you use the iOS app to import your LinkedIn connections into your contact list and then sync the iOS contacts into your Mac.\r\n\r\n## How to use it\r\n\r\n1. Download the app.\r\n2. Move it to the Applications folder.\r\n3. Run it once.\r\n\r\nIt doesn't have any UI but running it ensure that the app is registered to the system's LaunchServices database.\r\n\r\nThe next time you click on a `linkedin://#profile/xxxx` URL, it should open the contact's LinkedIn profile in your default web browser.\r\n\r\n**OpenLinkedIn** is brought to you by Basil Salad Software <http://basilsalad.com>. This app nor Basil Salad software is not affiliated with LinkedIn Inc.\r\n","name":"Openlinkedin","google":"","tagline":"Handles LinkedIn's proprietary iOS app URL","note":"Don't delete this file! It's used internally to help with page regeneration."}